pyseg2/__init__.py
pyseg2/binaryblocks.py
pyseg2/rawseg2.py
pyseg2/seg2file.py
pyseg2/toobspy.py
pyseg2-1.4.7.dist-info/licenses/LICENSE
pyseg2-1.4.7.dist-info/METADATA
pyseg2-1.4.7.dist-info/WHEEL
pyseg2-1.4.7.dist-info/top_level.txt
pyseg2-1.4.7.dist-info/RECORD
