Metadata-Version: 2.4
Name: pyseg2
Version: 1.4.7
Summary: Standalone package to read/write seg2 files in python
Author-email: Maximilien Lehujeur <maximilien.lehujeur@univ-eiffel.fr>
License: GPL3
Classifier: Programming Language :: Python :: 3
Classifier: Operating System :: POSIX :: Linux
Classifier: Operating System :: Microsoft :: Windows
Requires-Python: >=3.2
License-File: LICENSE
Requires-Dist: numpy
Dynamic: license-file
